{
    "res": {
        "jquery": {
            "uri": "/static/js/jquery.js",
            "type": "js",
            "extras": {
                "moduleId": "jquery"
            }
        },
        "static/js/require.js": {
            "uri": "/static/js/require.js",
            "type": "js"
        },
        "static/modules/base.js": {
            "uri": "/static/modules/base.js",
            "type": "js",
            "extras": {
                "moduleId": "base"
            },
            "deps": [
                "static/js/require.js",
                "jquery",
                "static/js/jquery-3.1.0.js"
            ],
            "pkg": "p0"
        },
        "static/modules/ui/tabs.js": {
            "uri": "/static/modules/ui/tabs.js",
            "type": "js",
            "extras": {
                "moduleId": "ui/tabs"
            },
            "deps": [
                "static/js/require.js",
                "jquery"
            ],
            "pkg": "p0"
        },
        "static/modules/ui/timeline.js": {
            "uri": "/static/modules/ui/timeline.js",
            "type": "js",
            "extras": {
                "moduleId": "ui/timeline"
            },
            "pkg": "p0"
        },
        "tests/async.js": {
            "uri": "/tests/async.js",
            "type": "js",
            "deps": [
                "q"
            ]
        },
        "views/index.html": {
            "uri": "/views/index.html",
            "type": "html",
            "extras": {
                "async": [
                    "static/modules/base.js",
                    "jquery",
                    "widget/header/header.js",
                    "static/modules/ui/tabs.js"
                ]
            }
        },
        "views/index.jade": {
            "uri": "/views/index.jade",
            "type": "jade"
        },
        "widget/header/header.css": {
            "uri": "/static/widget/header/header.css",
            "type": "css"
        },
        "widget/header/header.html": {
            "uri": "/widget/header/header.html",
            "type": "html",
            "deps": [
                "widget/header/header.js",
                "widget/header/header.css"
            ]
        },
        "widget/header/header.js": {
            "uri": "/static/widget/header/header.js",
            "type": "js",
            "extras": {
                "moduleId": "widget/header/header"
            },
            "deps": [
                "static/modules/ui/tabs.js",
                "widget/header/header.css"
            ]
        }
    },
    "pkg": {
        "p0": {
            "uri": "/static/vendor.js",
            "type": "js",
            "has": [
                "static/modules/base.js",
                "static/modules/ui/tabs.js",
                "static/modules/ui/timeline.js"
            ],
            "deps": [
                "static/js/require.js",
                "jquery",
                "static/js/jquery-3.1.0.js"
            ]
        }
    }
}
